{
    "key": "group_59297c5fe1aa8",
    "title": "Featured Image Position",
    "fields": [
        {
            "key": "field_59297c6bb5a82",
            "label": "",
            "name": "ft_img_position",
            "type": "select",
            "instructions": "",
            "required": 0,
            "conditional_logic": 0,
            "wrapper": {
                "width": "",
                "class": "",
                "id": ""
            },
            "choices": {
                "post-mast-bg": "Background Image",
                "post-mast-img": "After Title"
            },
            "default_value": [
                
            ],
            "allow_null": 0,
            "multiple": 0,
            "ui": 0,
            "ajax": 0,
            "return_format": "value",
            "placeholder": ""
        }
    ],
    "location": [
        [
            {
                "param": "post_type",
                "operator": "==",
                "value": "post"
            }
        ]
    ],
    "menu_order": 0,
    "position": "side",
    "style": "default",
    "label_placement": "top",
    "instruction_placement": "label",
    "hide_on_screen": "",
    "active": 1,
    "description": "",
    "modified": 1495892427
}